semgrep_rules_manager/__init__.py
semgrep_rules_manager/cli.py
semgrep_rules_manager/core.py
semgrep_rules_manager/data/index.json
semgrep_rules_manager/data/sources.yaml
semgrep_rules_manager/exception.py
semgrep_rules_manager/helpers.py
semgrep_rules_manager/rule.py
semgrep_rules_manager/rules_file.py
semgrep_rules_manager/sources.py
semgrep_rules_manager-0.4.0.dist-info/METADATA
semgrep_rules_manager-0.4.0.dist-info/WHEEL
semgrep_rules_manager-0.4.0.dist-info/entry_points.txt
semgrep_rules_manager-0.4.0.dist-info/licenses/LICENSE
semgrep_rules_manager-0.4.0.dist-info/RECORD
