Metadata-Version: 2.4
Name: semgrep_rules_manager
Version: 0.4.0
Summary: Manager of third-party Semgrep rules
License: MIT
License-File: LICENSE
Keywords: semgrep,semgrep-rules,semgrep-rules-manager,sast
Author: George-Andrei Iosif
Author-email: andrei.iosif@canonical.com
Requires-Python: >=3.10,<4.0
Classifier: Environment :: Console
Classifier: License :: OSI Approved :: MIT License
Classifier: Operating System :: OS Independent
Classifier: Programming Language :: Python :: 3
Classifier: Programming Language :: Python :: 3.10
Classifier: Programming Language :: Python :: 3.11
Classifier: Programming Language :: Python :: 3.12
Classifier: Programming Language :: Python :: 3.13
Classifier: Programming Language :: Python :: 3.14
Classifier: Topic :: Security
Classifier: Topic :: Software Development :: Libraries :: Python Modules
Classifier: Topic :: Software Development :: Quality Assurance
Classifier: Topic :: System :: Software Distribution
Requires-Dist: click (>=8.1.6,<9.0.0)
Requires-Dist: gitpython (>=3.1.32,<4.0.0)
Requires-Dist: pyyaml (>=6.0.1,<7.0.0)
Requires-Dist: rich (>=13.4.2,<14.0.0)
Project-URL: Repository, https://github.com/iosifache/semgrep-rules-manager
